FMLite-0.0.2.dist-info/DESCRIPTION.rst
FMLite-0.0.2.dist-info/METADATA
FMLite-0.0.2.dist-info/RECORD
FMLite-0.0.2.dist-info/WHEEL
FMLite-0.0.2.dist-info/metadata.json
FMLite-0.0.2.dist-info/top_level.txt
fmlite/__init__.py
fmlite/constants.py
fmlite/core.py
