Metadata-Version: 2.0
Name: FMLite
Version: 0.0.2
Summary: Pure Python Implementation of Factoriazatin Machine.
Home-page: https://github.com/moriaki3193/FMLite
Author: moriaki3193
Author-email: moriaki3193@gmail.com
License: Type license() to see the full license text
Platform: UNKNOWN
